odoo/addons/pos_journal_image/README.rst
odoo/addons/pos_journal_image/__init__.py
odoo/addons/pos_journal_image/__manifest__.py
odoo/addons/pos_journal_image/i18n/ca.po
odoo/addons/pos_journal_image/i18n/ca_ES.po
odoo/addons/pos_journal_image/i18n/es.po
odoo/addons/pos_journal_image/i18n/fr.po
odoo/addons/pos_journal_image/i18n/pos_journal_image.pot
odoo/addons/pos_journal_image/migrations/12.0.1.0.0/post-migration.py
odoo/addons/pos_journal_image/migrations/12.0.1.0.0/pre-migration.py
odoo/addons/pos_journal_image/models/__init__.py
odoo/addons/pos_journal_image/models/account_journal.py
odoo/addons/pos_journal_image/readme/CONFIGURE.rst
odoo/addons/pos_journal_image/readme/CONTRIBUTORS.rst
odoo/addons/pos_journal_image/readme/DESCRIPTION.rst
odoo/addons/pos_journal_image/static/description/account_journal_form.png
odoo/addons/pos_journal_image/static/description/icon.png
odoo/addons/pos_journal_image/static/description/index.html
odoo/addons/pos_journal_image/static/description/pos_payment.png
odoo/addons/pos_journal_image/static/src/css/pos_journal_image.css
odoo/addons/pos_journal_image/static/src/js/pos_journal_image.js
odoo/addons/pos_journal_image/static/src/xml/pos_journal_image.xml
odoo/addons/pos_journal_image/views/templates.xml
odoo/addons/pos_journal_image/views/view_account_journal.xml
odoo12_addon_pos_journal_image-12.0.1.0.2.dist-info/METADATA
odoo12_addon_pos_journal_image-12.0.1.0.2.dist-info/WHEEL
odoo12_addon_pos_journal_image-12.0.1.0.2.dist-info/top_level.txt
odoo12_addon_pos_journal_image-12.0.1.0.2.dist-info/RECORD
